MANIFEST.in
README.md
setup.py
frs/__init__.py
frs/api.py
frs/app.py
frs/crypto.py
frs/docs.py
frs/errors.py
frs/loader.py
frs/resource.py
frs/validators.py
frs.egg-info/PKG-INFO
frs.egg-info/SOURCES.txt
frs.egg-info/dependency_links.txt
frs.egg-info/entry_points.txt
frs.egg-info/not-zip-safe
frs.egg-info/top_level.txt
frs/static/index.html
frs/static/o2c.html
frs/static/swagger-ui.js
frs/static/swagger-ui.min.js
frs/static/css/print.css
frs/static/css/reset.css
frs/static/css/screen.css
frs/static/css/style.css
frs/static/css/typography.css
frs/static/fonts/DroidSans-Bold.ttf
frs/static/fonts/DroidSans.ttf
frs/static/images/collapse.gif
frs/static/images/expand.gif
frs/static/images/explorer_icons.png
frs/static/images/favicon-16x16.png
frs/static/images/favicon-32x32.png
frs/static/images/favicon.ico
frs/static/images/logo_small.png
frs/static/images/pet_store_api.png
frs/static/images/throbber.gif
frs/static/images/wordnik_api.png
frs/static/lang/en.js
frs/static/lang/es.js
frs/static/lang/fr.js
frs/static/lang/it.js
frs/static/lang/ja.js
frs/static/lang/pl.js
frs/static/lang/pt.js
frs/static/lang/ru.js
frs/static/lang/tr.js
frs/static/lang/translator.js
frs/static/lang/zh-cn.js
frs/static/lib/backbone-min.js
frs/static/lib/handlebars-2.0.0.js
frs/static/lib/highlight.7.3.pack.js
frs/static/lib/jquery-1.8.0.min.js
frs/static/lib/jquery.ba-bbq.min.js
frs/static/lib/jquery.slideto.min.js
frs/static/lib/jquery.wiggle.min.js
frs/static/lib/jsoneditor.min.js
frs/static/lib/marked.js
frs/static/lib/swagger-oauth.js
frs/static/lib/underscore-min.js
frs/static/lib/underscore-min.map