Metadata-Version: 1.1
Name: frs
Version: 0.0.0.dev18
Summary: Flask-RESTful Swagger(-driven) Validation
Home-page: UNKNOWN
Author: Rick Copeland
Author-email: rick@arborian.com
License: UNKNOWN
Platform: UNKNOWN
Classifier: Programming Language :: Python
